patch_aiohttp_requests.py
patch_aiohttp_requests-0.1.1.dist-info/LICENSE.md
patch_aiohttp_requests-0.1.1.dist-info/METADATA
patch_aiohttp_requests-0.1.1.dist-info/WHEEL
patch_aiohttp_requests-0.1.1.dist-info/top_level.txt
patch_aiohttp_requests-0.1.1.dist-info/RECORD
