Metadata-Version: 2.1
Name: patch-aiohttp-requests
Version: 0.1.1
Summary: Simple patching of `aiohttp` requests
Home-page: https://github.com/Raekkeri/patch-aiohttp-requests
Author: Teemu Husso
Author-email: teemu.husso@gmail.com
Keywords: aiohttp,requests,tests,mock,patch
License-File: LICENSE.md
Requires-Dist: setuptools
